{
  "projectId": "gen-lang-client-0105737183",
  "appId": "1:100892974326:web:da7a01b142ccceb19060d7",
  "apiKey": "AIzaSyAZEnJOLnAp6SrLI5LEXGQKSeQ4Utp6NKM",
  "authDomain": "gen-lang-client-0105737183.firebaseapp.com",
  "firestoreDatabaseId": "ai-studio-remixontariopare-6e5e99c8-069c-4104-a4c3-e16f1413e29b",
  "storageBucket": "gen-lang-client-0105737183.firebasestorage.app",
  "messagingSenderId": "100892974326",
  "measurementId": "",
  "oAuthClientId": "100892974326-870ams6r87n5bff2iitikoo9figivsvo.apps.googleusercontent.com"
}